[
{
"question_en": "Consider the following statements:\n1. Indian Constitution is the lengthiest written constitution.\n2. It is completely rigid.\nWhich is correct?",
"question_ta": "கூற்றுகள்:\n1. இந்திய அரசியலமைப்பு நீளமானது.\n2. இது முழுவதும் கடினமானது.\nசரி எது?",
"options_en": ["1 only","2 only","Both","None"],
"options_ta": ["1 மட்டும்","2 மட்டும்","இரண்டும்","இல்லை"],
"answer": "a",
"explanation_en": "It is lengthiest but not completely rigid.",
"explanation_ta": "நீளமானது ஆனால் முழு கடினம் அல்ல.",
"subject": "POLITY",
"topic": "features_of_constitution"
},

{
"question_en": "Consider:\n1. Parliamentary system is borrowed from UK\n2. Fundamental Rights from USA\n3. DPSP from Ireland\nChoose correct",
"question_ta": "கூற்றுகள்:\n1. UK – பாராளுமன்றம்\n2. USA – உரிமைகள்\n3. Ireland – DPSP\nசரி?",
"options_en": ["1,2,3","1,2","2,3","1,3"],
"options_ta": ["1,2,3","1,2","2,3","1,3"],
"answer": "a",
"explanation_en": "All are correct borrowings.",
"explanation_ta": "அனைத்தும் சரி.",
"subject": "POLITY",
"topic": "features_of_constitution"
},

{
"question_en": "Assertion: Indian Constitution is federal.\nReason: There is division of powers between Centre and States.",
"question_ta": "Assertion: இந்தியா கூட்டாட்சி.\nReason: அதிகாரப் பிரிவு உள்ளது.",
"options_en": ["Both true and R explains A","Both true not explanation","A true R false","A false R true"],
"options_ta": ["இரண்டும் சரி காரணம்","இரண்டும் சரி காரணம் இல்லை","A சரி R தவறு","A தவறு R சரி"],
"answer": "a",
"explanation_en": "Division of powers makes it federal.",
"explanation_ta": "அதிகாரப் பிரிவு காரணம்.",
"subject": "POLITY",
"topic": "features_of_constitution"
},

{
"question_en": "Assertion: Indian Constitution has unitary features.\nReason: Centre becomes strong during emergency.",
"question_ta": "Assertion: இந்தியா ஒருங்கிணைந்த அம்சங்கள் கொண்டது.\nReason: அவசரநிலையில் மத்திய அரசு வலுவாகிறது.",
"options_en": ["Both true and R explains A","Both true not explanation","A true R false","A false R true"],
"options_ta": ["இரண்டும் சரி காரணம்","இரண்டும் சரி காரணம் இல்லை","A சரி R தவறு","A தவறு R சரி"],
"answer": "a",
"explanation_en": "Emergency provisions create unitary bias.",
"explanation_ta": "அவசரநிலை காரணம்.",
"subject": "POLITY",
"topic": "features_of_constitution"
},

{
"question_en": "Consider:\n1. DPSP are enforceable by courts\n2. Fundamental Rights are enforceable\nCorrect?",
"question_ta": "கூற்றுகள்:\n1. DPSP அமல்படுத்தப்படும்\n2. உரிமைகள் அமல்படுத்தப்படும்\nசரி?",
"options_en": ["2 only","1 only","Both","None"],
"options_ta": ["2 மட்டும்","1 மட்டும்","இரண்டும்","இல்லை"],
"answer": "a",
"explanation_en": "DPSP not enforceable.",
"explanation_ta": "DPSP அமலில்லை.",
"subject": "POLITY",
"topic": "features_of_constitution"
},

{
"question_en": "Assertion: President is real executive.\nReason: He exercises actual powers.",
"question_ta": "Assertion: தலைவர் உண்மையான நிர்வாகம்.\nReason: அவர் அதிகாரம் பயன்படுத்துகிறார்.",
"options_en": ["A false R false","A false R true","A true R false","Both true"],
"options_ta": ["A தவறு R தவறு","A தவறு R சரி","A சரி R தவறு","இரண்டும் சரி"],
"answer": "b",
"explanation_en": "President is nominal; real power lies with Council of Ministers.",
"explanation_ta": "அவர் பெயரளவு தலைவர்.",
"subject": "POLITY",
"topic": "features_of_constitution"
},

{
"question_en": "Consider:\n1. India has single citizenship\n2. It promotes unity\nCorrect?",
"question_ta": "கூற்றுகள்:\n1. ஒற்றை குடியுரிமை\n2. ஒற்றுமை வளர்ச்சி\nசரி?",
"options_en": ["Both","1 only","2 only","None"],
"options_ta": ["இரண்டும்","1 மட்டும்","2 மட்டும்","இல்லை"],
"answer": "a",
"explanation_en": "Single citizenship ensures unity.",
"explanation_ta": "ஒற்றுமை தருகிறது.",
"subject": "POLITY",
"topic": "features_of_constitution"
},

{
"question_en": "Assertion: Judiciary is independent.\nReason: Executive controls judiciary.",
"question_ta": "Assertion: நீதித்துறை சுயாதீனம்.\nReason: நிர்வாகம் கட்டுப்படுத்துகிறது.",
"options_en": ["A true R false","A false R true","Both true","Both false"],
"options_ta": ["A சரி R தவறு","A தவறு R சரி","இரண்டும் சரி","இரண்டும் தவறு"],
"answer": "a",
"explanation_en": "Judiciary is independent; not controlled.",
"explanation_ta": "சுயாதீனம் உள்ளது.",
"subject": "POLITY",
"topic": "features_of_constitution"
},

{
"question_en": "Consider:\n1. Constitution is flexible\n2. Constitution is rigid\nCorrect?",
"question_ta": "கூற்றுகள்:\n1. நெகிழ்வு\n2. கடினம்\nசரி?",
"options_en": ["Both","1 only","2 only","None"],
"options_ta": ["இரண்டும்","1 மட்டும்","2 மட்டும்","இல்லை"],
"answer": "a",
"explanation_en": "Combination of both.",
"explanation_ta": "இரண்டும் உள்ளது.",
"subject": "POLITY",
"topic": "features_of_constitution"
},

{
"question_en": "Assertion: Indian Constitution borrowed features.\nReason: It is copied entirely.",
"question_ta": "Assertion: பல அம்சங்கள் எடுத்தது.\nReason: முழுவதும் நகல்.",
"options_en": ["A true R false","A false R true","Both true","Both false"],
"options_ta": ["A சரி R தவறு","A தவறு R சரி","இரண்டும் சரி","இரண்டும் தவறு"],
"answer": "a",
"explanation_en": "Borrowed but not copied entirely.",
"explanation_ta": "முழு நகல் இல்லை.",
"subject": "POLITY",
"topic": "features_of_constitution"
}

]